bucketcloner/__init__.py
bucketcloner/main.py
bucketcloner/py.typed
bucketcloner-0.3.0.dist-info/WHEEL
bucketcloner-0.3.0.dist-info/entry_points.txt
bucketcloner-0.3.0.dist-info/METADATA
bucketcloner-0.3.0.dist-info/RECORD
