Metadata-Version: 2.3
Name: bucketcloner
Version: 0.3.0
Summary: Clone all repositories from a Bitbucket workspace.
Author: Philipp Lies
Author-email: Philipp Lies <phil@lies.io>
Classifier: Programming Language :: Python :: 3
Classifier: Development Status :: 4 - Beta
Classifier: License :: OSI Approved :: GNU General Public License v3 (GPLv3)
Classifier: Operating System :: OS Independent
Requires-Dist: gitpython>=3.1.45
Requires-Dist: requests>=2.32.4
Requires-Python: >=3.8
Project-URL: Bug Tracker, https://github.com/phillies/bucketcloner/issues
Project-URL: Homepage, https://github.com/phillies/bucketcloner
